shc_utilities/__init__.py
shc_utilities/config_utils/__init__.py
shc_utilities/config_utils/config_log_loader.py
shc_utilities-0.1.1.dist-info/METADATA
shc_utilities-0.1.1.dist-info/WHEEL
shc_utilities-0.1.1.dist-info/top_level.txt
shc_utilities-0.1.1.dist-info/RECORD
