Metadata-Version: 2.1
Name: shc-utilities
Version: 0.1.1
Summary: Utilities for working config and logger
